{"data":{"site":{"siteMetadata":{"author":{"name":"kwansik Kim / Austin","bio":"FrontEnd Web Devleoper","photo":"/photo.jpg","contacts":{"facebook":"#","linkedin":"","github":"kwansikdev","twitter":"","telegram":"","instagram":"kkwans__","email":"","rss":"","vkontakte":"","line":"","gitlab":"","weibo":"","codepen":"","youtube":""}},"menu":[{"label":"Articles","path":"/"},{"label":"Tags","path":"/tags"},{"label":"About me","path":"/pages/about"},{"label":"Contact me","path":"/pages/contacts"}],"url":"https://kwansikdev.github.io","title":"Blog by kwansikdev","subtitle":"","copyright":"© All rights reserved.","disqusShortname":""}}}}